jiri_destkird/__init__.py
jiri_destkird/file_utils.py
jiri_destkird/image_utils.py
jiri_destkird/utils/__init__.py
jiri_destkird/utils/importer.py
jiri_destkird-0.0.5.dist-info/METADATA
jiri_destkird-0.0.5.dist-info/WHEEL
jiri_destkird-0.0.5.dist-info/top_level.txt
jiri_destkird-0.0.5.dist-info/RECORD
