Metadata-Version: 2.4
Name: jiri_destkird
Version: 0.0.5
Summary: Jiri Destkird: The ultimate Python toolkit for streamlining Deep Learning & Computer Vision workflows.
Author-email: Arman_karimpanah <armankarimpanah@gmail.com>
Project-URL: Homepage, https://github.com/karimpanah/jiri_destkird
Project-URL: Repository, https://github.com/karimpanah/jiri_destkird
Project-URL: Issues, https://github.com/karimpanah/jiri_destkird/issues
Classifier: Programming Language :: Python :: 3
Classifier: License :: OSI Approved :: MIT License
Classifier: Operating System :: OS Independent
Classifier: Topic :: Scientific/Engineering :: Artificial Intelligence
Classifier: Topic :: Scientific/Engineering :: Image Processing
Requires-Python: >=3.8
Requires-Dist: numpy<2.0.0
Requires-Dist: opencv-python-headless>=4.5.0
Requires-Dist: Pillow>=9.0
Requires-Dist: matplotlib>=3.5.0
